{
    "version": "5.0.3",
    "description": "Browser Tamer. Opens required browser based on configuration",
    "homepage": "https://www.aloneguid.uk/projects/bt/",
    "license": "Freeware",
    "changelog": "https://github.com/aloneguid/bt/releases",
    "architecture": {
        "64bit": {
            "url": "https://github.com/aloneguid/bt/releases/download/5.0.3/bt-5.0.3.zip",
            "hash": "ec545036acb8289e58a9a57bb637ee078acd35a113d16daebe4bc775ce885de8"
        }
    },
    "bin": "bt.exe",
    "shortcuts": [
        [
            "bt.exe",
            "Browser Tamer"
        ]
    ],
    "checkver": {
        "github": "https://github.com/aloneguid/bt"
    },
    "autoupdate": {
        "architecture": {
            "64bit": {
                "url": "https://github.com/aloneguid/bt/releases/download/$version/bt-$version.zip"
            }
        },
        "hash": {
            "url": "$url.sha256.txt",
            "regex": "$sha256"
        }
    }
}
