{
    "version": "0.20.1489",
    "description": "Jacket. API Support for your favorite torrent trackers",
    "homepage": "https://github.com/Jackett/Jackett",
    "license": "GPL-2.0-or-later",
    "changelog": "https://github.com/Jackett/Jackett/releases",
    "url": "https://github.com/Jackett/Jackett/releases/download/v0.20.1489/Jackett.Binaries.Windows.zip",
    "hash": "f63c17dd34b7f51a87eb72e5af67dc8452c3d607ee4543b96cfedb1eee287890",
    "shortcuts": [
        [
            "Jackett\\JackettTray.exe",
            "Jackett"
        ]
    ],
    "checkver": "github",
    "autoupdate": {
        "url": "https://github.com/Jackett/Jackett/releases/download/v$version/Jackett.Binaries.Windows.zip"
    }
}
