{
    "version": ".",
    "description": "Sordum's Qemu Simple Boot. Quickly test images in Qemu.",
    "homepage": "https://www.sordum.org/qemu-simple-boot",
    "license": {
        "identifier": "Freeware",
        "url": "https://www.sordum.org/eula/"
    },
    "url": "https://www.sordum.org/files/qemu-simple-boot/qsiboot_v..zip",
    "hash": "3ae158518c5086ee56c84222af75f606ab4e061e3c444f0be35093199cc1f1a8",
    "extract_dir": "qsib_v.",
    "shortcuts": [
        [
            "Qsib.exe",
            "Sordum\\Qemu Simple Boot"
        ]
    ],
    "persist": "qemu\\Qsib.ini",
    "checkver": "v([\\d.]+)",
    "autoupdate": {
        "url": "https://www.sordum.org/files/qemu-simple-boot/qsiboot_v$version.zip",
        "extract_dir": "qsib_v$version"
    }
}
